odoo/addons/l10n_nl_tax_statement_icp_split/README.rst
odoo/addons/l10n_nl_tax_statement_icp_split/__init__.py
odoo/addons/l10n_nl_tax_statement_icp_split/__manifest__.py
odoo/addons/l10n_nl_tax_statement_icp_split/data/ir_actions_report.xml
odoo/addons/l10n_nl_tax_statement_icp_split/i18n/l10n_nl_tax_statement_icp_split.pot
odoo/addons/l10n_nl_tax_statement_icp_split/models/__init__.py
odoo/addons/l10n_nl_tax_statement_icp_split/models/account_move.py
odoo/addons/l10n_nl_tax_statement_icp_split/models/account_move_line.py
odoo/addons/l10n_nl_tax_statement_icp_split/models/l10n_nl_icp_statement.py
odoo/addons/l10n_nl_tax_statement_icp_split/models/l10n_nl_vat_statement.py
odoo/addons/l10n_nl_tax_statement_icp_split/models/l10n_nl_vat_statement_icp_line.py
odoo/addons/l10n_nl_tax_statement_icp_split/models/l10n_nl_vat_statement_line.py
odoo/addons/l10n_nl_tax_statement_icp_split/readme/CONTEXT.md
odoo/addons/l10n_nl_tax_statement_icp_split/readme/CONTRIBUTORS.md
odoo/addons/l10n_nl_tax_statement_icp_split/readme/DESCRIPTION.md
odoo/addons/l10n_nl_tax_statement_icp_split/readme/USAGE.md
odoo/addons/l10n_nl_tax_statement_icp_split/security/ir.model.access.csv
odoo/addons/l10n_nl_tax_statement_icp_split/static/description/icon.png
odoo/addons/l10n_nl_tax_statement_icp_split/static/description/index.html
odoo/addons/l10n_nl_tax_statement_icp_split/tests/__init__.py
odoo/addons/l10n_nl_tax_statement_icp_split/tests/test_l10n_nl_tax_statement_icp_split.py
odoo/addons/l10n_nl_tax_statement_icp_split/views/l10n_nl_icp_statement.xml
odoo/addons/l10n_nl_tax_statement_icp_split/views/l10n_nl_vat_statement.xml
odoo_addon_l10n_nl_tax_statement_icp_split-16.0.1.0.0.2.dist-info/METADATA
odoo_addon_l10n_nl_tax_statement_icp_split-16.0.1.0.0.2.dist-info/WHEEL
odoo_addon_l10n_nl_tax_statement_icp_split-16.0.1.0.0.2.dist-info/top_level.txt
odoo_addon_l10n_nl_tax_statement_icp_split-16.0.1.0.0.2.dist-info/RECORD
