Metadata-Version: 2.1
Name: odoo-addon-l10n_nl_tax_statement_icp_split
Version: 16.0.1.0.0.2
Summary: Manage your BTW and ICP statements separately
Home-page: https://github.com/OCA/l10n-netherlands
Author: Hunki Enterprises BV, Odoo Community Association (OCA)
Author-email: support@odoo-community.org
License: AGPL-3
Classifier: Programming Language :: Python
Classifier: Framework :: Odoo
Classifier: Framework :: Odoo :: 16.0
Classifier: License :: OSI Approved :: GNU Affero General Public License v3
Classifier: Development Status :: 3 - Alpha
Requires-Python: >=3.10
Requires-Dist: odoo-addon-l10n-nl-tax-statement-icp<16.1dev,>=16.0dev
Requires-Dist: odoo<16.1dev,>=16.0a
